kiwiclient/__init__.py
kiwiclient/__main__.py
kiwiclient-1.0.11.dist-info/METADATA
kiwiclient-1.0.11.dist-info/RECORD
kiwiclient-1.0.11.dist-info/WHEEL
kiwiclient-1.0.11.dist-info/top_level.txt
